jsoninput/InputHandler.py
jsoninput/__init__.py
jsoninput/input_handler.py
jsoninput-0.0.2.dist-info/LICENSE
jsoninput-0.0.2.dist-info/METADATA
jsoninput-0.0.2.dist-info/WHEEL
jsoninput-0.0.2.dist-info/top_level.txt
jsoninput-0.0.2.dist-info/RECORD
